keios_protocol_gensim/__init__.py
keios_protocol_gensim/fasttext_embedding.py
keios_protocol_gensim/fasttext_most_similar.py
keios_protocol_gensim/fasttext_similarity.py
keios_protocol_gensim/fbs/EmbeddingElement.py
keios_protocol_gensim/fbs/EmbeddingRequest.py
keios_protocol_gensim/fbs/EmbeddingResponse.py
keios_protocol_gensim/fbs/GensimFastTextEmbeddingRequest.py
keios_protocol_gensim/fbs/GensimFastTextEmbeddingResponse.py
keios_protocol_gensim/fbs/GensimFastTextMostSimilarRequest.py
keios_protocol_gensim/fbs/GensimFastTextMostSimilarResponse.py
keios_protocol_gensim/fbs/GensimFastTextSimilarityRequest.py
keios_protocol_gensim/fbs/GensimFastTextSimilarityResponse.py
keios_protocol_gensim/fbs/GensimMessage.py
keios_protocol_gensim/fbs/GensimMessageType.py
keios_protocol_gensim/fbs/MostSimilarRequest.py
keios_protocol_gensim/fbs/MostSimilarResponse.py
keios_protocol_gensim/fbs/MostSimilarity.py
keios_protocol_gensim/fbs/SimilarityRequest.py
keios_protocol_gensim/fbs/SimilarityResponse.py
keios_protocol_gensim/typed_message.py
keios_protocol_gensim-1.1.0.dist-info/WHEEL
keios_protocol_gensim-1.1.0.dist-info/METADATA
keios_protocol_gensim-1.1.0.dist-info/RECORD
